{
    "texto": "Hola, somos el grupo de jovenes programadores llamado Miwuff, que hemos creado la pagina web de la tienda de Miwuff, en caso de cualquier  duda o necesidad. No dudeis en contactar con nosotros usando el contacto que le facilitamos, un poco más abajo. Tambien podeis visitarnos en nuestra tienda fisica.",
    "Contacto": "Nombre y Apellidos",
    "Email": "Correo Electrónico",
    "Numero de Telefono": "Numero de telefono",
    "Telefono de contacto": "Telefono de contacto",
    "Direccion de la tienda": "Direccion de la tienda"
}   